kiwiaga/__init__.py
kiwiaga/cli.py
kiwiaga/config.py
kiwiaga/manga.py
kiwiaga-0.1.0.dist-info/LICENSE
kiwiaga-0.1.0.dist-info/METADATA
kiwiaga-0.1.0.dist-info/WHEEL
kiwiaga-0.1.0.dist-info/entry_points.txt
kiwiaga-0.1.0.dist-info/RECORD
