Metadata-Version: 2.1
Name: kiwiaga
Version: 0.1.0
Summary: A CLI tool designed for interact with MangaDex API and show info about manga.
Author: febits
Author-email: febits@proton.me
Requires-Python: >=3.12,<4.0
Classifier: Programming Language :: Python :: 3
Classifier: Programming Language :: Python :: 3.12
Requires-Dist: httpx (>=0.27.0,<0.28.0)
Requires-Dist: humanize (>=4.9.0,<5.0.0)
Requires-Dist: pytz (>=2024.1,<2025.0)
Requires-Dist: pyyaml (>=6.0.1,<7.0.0)
Requires-Dist: rich (>=13.7.1,<14.0.0)
Requires-Dist: typer (>=0.12.3,<0.13.0)
